opticalmarkmedi/__init__.py
opticalmarkmedi-0.2.dist-info/METADATA
opticalmarkmedi-0.2.dist-info/WHEEL
opticalmarkmedi-0.2.dist-info/top_level.txt
opticalmarkmedi-0.2.dist-info/RECORD
