Metadata-Version: 1.0
Name: opticalmarkmedi
Version: 0.2
Summary: Optical mark for Meditech
Home-page: https://gitlab.com/trunghd828/optical_mark
Author: Tiamo
Author-email: trunghd828@gmail.com
License: None
Platform: UNKNOWN
